desdeo_mcdm/.readthedocs.yml
desdeo_mcdm/__init__.py
desdeo_mcdm/approximation/PAINT.py
desdeo_mcdm/approximation/__init__.py
desdeo_mcdm/interactive/ENautilus.py
desdeo_mcdm/interactive/InteractiveMethod.py
desdeo_mcdm/interactive/NIMBUS.py
desdeo_mcdm/interactive/Nautilus.py
desdeo_mcdm/interactive/NautilusNavigator.py
desdeo_mcdm/interactive/NautilusV2.py
desdeo_mcdm/interactive/ParetoNavigator.py
desdeo_mcdm/interactive/ReferencePointMethod.py
desdeo_mcdm/interactive/__init__.py
desdeo_mcdm/utilities/__init__.py
desdeo_mcdm/utilities/solvers.py
desdeo_mcdm-1.3.3.dist-info/LICENSE
desdeo_mcdm-1.3.3.dist-info/METADATA
desdeo_mcdm-1.3.3.dist-info/WHEEL
desdeo_mcdm-1.3.3.dist-info/RECORD
