Metadata-Version: 2.1
Name: desdeo-mcdm
Version: 1.3.3
Summary: Contains traditional optimization techniques from the field of Multiple-criteria decision-making. Methods belonging to the NIMBUS and NAUTILUS families can be found here. Part of the DESDEO framework.
License: MIT
Author: Giovanni Misitano
Requires-Python: >=3.9,<3.11
Classifier: License :: OSI Approved :: MIT License
Classifier: Programming Language :: Python :: 3
Classifier: Programming Language :: Python :: 3.9
Classifier: Programming Language :: Python :: 3.10
Requires-Dist: desdeo-problem (>=1.5)
Requires-Dist: desdeo-tools (>=1.8)
